Classfile /Users/zionchilagan/workspace/j--/Test.class
  Last modified Apr 19, 2024; size 434 bytes
  SHA-256 checksum ed9f1103a695aac80a076679350913de7ed33f68f9ebfff4994b6bc4d4fe63e4
public class Test
  minor version: 0
  major version: 49
  flags: (0x0001) ACC_PUBLIC
  this_class: #2                          // Test
  super_class: #4                         // java/lang/Object
  interfaces: 0, fields: 0, methods: 3, attributes: 0
Constant pool:
   #1 = Utf8               Test
   #2 = Class              #1             // Test
   #3 = Utf8               java/lang/Object
   #4 = Class              #3             // java/lang/Object
   #5 = Utf8               <init>
   #6 = Utf8               ()V
   #7 = NameAndType        #5:#6          // "<init>":()V
   #8 = Methodref          #4.#7          // java/lang/Object."<init>":()V
   #9 = Utf8               Code
  #10 = Utf8               main
  #11 = Utf8               ([Ljava/lang/String;)V
  #12 = Double             5.0d
  #14 = Utf8               sqrt
  #15 = Utf8               (D)D
  #16 = NameAndType        #14:#15        // sqrt:(D)D
  #17 = Methodref          #2.#16         // Test.sqrt:(D)D
  #18 = Utf8               Exceptions
  #19 = Utf8               IllegalArgumentException
  #20 = Class              #19            // IllegalArgumentException
  #21 = Double             0.0d
  #23 = Utf8               java/lang/IllegalArgumentException
  #24 = Class              #23            // java/lang/IllegalArgumentException
  #25 = Utf8               x must be positve
  #26 = String             #25            // x must be positve
  #27 = Utf8               (Ljava/lang/String;)V
  #28 = NameAndType        #5:#27         // "<init>":(Ljava/lang/String;)V
  #29 = Methodref          #24.#28        // java/lang/IllegalArgumentException."<init>":(Ljava/lang/String;)V
  #30 = Double             3.0d
{
  public Test();
    descriptor: ()V
    flags: (0x0001) ACC_PUBLIC
    Code:
      stack=1, locals=1, args_size=1
         0: aload_0
         1: invokespecial #8                  // Method java/lang/Object."<init>":()V
         4: return

  public static void main(java.lang.String[]);
    descriptor: ([Ljava/lang/String;)V
    flags: (0x0009) ACC_PUBLIC, ACC_STATIC
    Code:
      stack=2, locals=1, args_size=1
         0: ldc2_w        #12                 // double 5.0d
         3: invokestatic  #17                 // Method sqrt:(D)D
         6: pop
         7: return

  private static double sqrt(double) throws IllegalArgumentException;
    descriptor: (D)D
    flags: (0x000a) ACC_PRIVATE, ACC_STATIC
    Exceptions:
      throws IllegalArgumentException
    Code:
      stack=4, locals=2, args_size=1
         0: dload_0
         1: ldc2_w        #21                 // double 0.0d
         4: dcmpg
         5: ifge          18
         8: new           #24                 // class java/lang/IllegalArgumentException
        11: dup
        12: ldc           #26                 // String x must be positve
        14: invokespecial #29                 // Method java/lang/IllegalArgumentException."<init>":(Ljava/lang/String;)V
        17: athrow
        18: ldc2_w        #30                 // double 3.0d
        21: dreturn
}
